altar_icons/__init__.py
altar_icons/_base.py
altar_icons/abstract.py
altar_icons/arrows.py
altar_icons/objects.py
pyaltar_icons-0.3.12.dist-info/METADATA
pyaltar_icons-0.3.12.dist-info/WHEEL
pyaltar_icons-0.3.12.dist-info/RECORD
