Metadata-Version: 2.4
Name: pyaltar-icons
Version: 0.3.12
Summary: Beautiful & consistent icon toolkit made for Aether apps.
Project-URL: homepage, https://github.com/pyaether/altar-icons
Project-URL: repository, https://github.com/pyaether/altar-icons
Project-URL: documentation, https://github.com/pyaether/altar-icons
Author-email: Saurabh Ghanekar <ghanekarsaurabh8@gmail.com>
License-Expression: BSD-2-Clause
Classifier: Operating System :: OS Independent
Classifier: Programming Language :: Python :: 3
Requires-Python: >=3.10
Requires-Dist: pyaether>=0.4
